rybak/__init__.py
rybak/_types.py
rybak/adapter.py
rybak/events.py
rybak/jinja.py
rybak/mako.py
rybak/py.typed
rybak/pycompat.py
rybak/tree_renderer.py
rybak-0.5.0.dist-info/METADATA
rybak-0.5.0.dist-info/WHEEL
rybak-0.5.0.dist-info/RECORD
