Metadata-Version: 2.3
Name: rybak
Version: 0.5.0
Summary: Directory-tree generator library
Project-URL: Repository, https://github.com/python-lapidary/rybak
Project-URL: Issues, https://github.com/python-lapidary/rybak/issues
Project-URL: Changelog, https://github.com/python-lapidary/rybak/blob/main/CHANGELOG.md
Author-email: Rafał Krupiński <rafalkrupinski@users.noreply.github.com>
Classifier: Development Status :: 3 - Alpha
Classifier: Intended Audience :: Developers
Classifier: License :: OSI Approved :: BSD License
Classifier: Operating System :: OS Independent
Classifier: Topic :: Utilities
Classifier: Typing :: Typed
Requires-Python: >=3.9
Requires-Dist: importlib-resources<7,>=5; python_version < '3.12'
Requires-Dist: typing-extensions>=4.9; python_version < '3.10'
Provides-Extra: jinja
Requires-Dist: jinja2<4,>=3; extra == 'jinja'
Provides-Extra: mako
Requires-Dist: mako<2,>=1; extra == 'mako'
